{"name":"SETS","fileName":"My Jumbo Commission Notebook.json","createdAt":"2024-08-08T20:46:08.921Z","cells":[{"id":"7b881ba474cc4835","type":"markdown","content":"**Notes**\n\n* Add some notes here\n* Use markdown"},{"id":"6a81fb63b6e2bcc5","type":"redis","content":"SADD colors red\r\nSADD colors red\r\nSADD colors blue\r\n\r\nSMEMBERS colors"},{"id":"1723150570313","type":"redis","content":"SADD col:1 red blue orange\r\nSADD col:2 blue green purple\r\nSADD col:3 blue red purple\r\n\r\nSUNION col:1 col:2 col:3"},{"id":"1723150718854","type":"redis","content":"SINTER col:1 col:2"},{"id":"1723150802524","type":"redis","content":"SDIFF col:1 col:2"},{"id":"1723151354799","type":"redis","content":"SINTERSTORE col:results col:1 col:2 col:3\r\n\r\nSMEMBERS col:results"},{"id":"1723151579664","type":"redis","content":"SDIFFSTORE coldiff:results col:1 col:2 col:3\r\n\r\nSMEMBERS coldiff:results"},{"id":"1723151650402","type":"redis","content":"SUNIONSTORE coluni:results col:1 col:2 col:3\r\n\r\nSMEMBERS coluni:results"},{"id":"1723151804911","type":"redis","content":"SISMEMBER coluni:results red"},{"id":"1723151981323","type":"redis","content":"SMISMEMBER coluni:results red  white blue"},{"id":"1723152128296","type":"redis","content":"SCARD coluni:results"},{"id":"1723152244184","type":"redis","content":"SREM coluni:results red\r\nSMISMEMBER coluni:results red"},{"id":"1723152442077","type":"redis","content":"SMEMBERS colors\r\n\r\nSSCAN colors 0 COUNT 2\r\n"}],"id":"db91f664e067afdc"}